package/__init__.py
package/main.py
harshita-0.1.0.dist-info/METADATA
harshita-0.1.0.dist-info/WHEEL
harshita-0.1.0.dist-info/license
harshita-0.1.0.dist-info/top_level.txt
harshita-0.1.0.dist-info/RECORD
